README.md
setup.py
v.txt
cosu/__init__.py
cosu/pso/__init__.py
cosu/pso/csip_access.py
cosu/pso/pso.py
cosu/utils/__init__.py
cosu/utils/trace_writer.py
cosu/utils/utils.py
cosu/utils/plot/__init__.py
cosu/utils/plot/cost_steps.py
csip_cosu.egg-info/PKG-INFO
csip_cosu.egg-info/SOURCES.txt
csip_cosu.egg-info/dependency_links.txt
csip_cosu.egg-info/not-zip-safe
csip_cosu.egg-info/requires.txt
csip_cosu.egg-info/top_level.txt
pyswarms/__init__.py
pyswarms/backend/__init__.py
pyswarms/backend/generators.py
pyswarms/backend/handlers.py
pyswarms/backend/operators.py
pyswarms/backend/swarms.py
pyswarms/backend/topology/__init__.py
pyswarms/backend/topology/base.py
pyswarms/backend/topology/pyramid.py
pyswarms/backend/topology/random.py
pyswarms/backend/topology/ring.py
pyswarms/backend/topology/star.py
pyswarms/backend/topology/von_neumann.py
pyswarms/base/__init__.py
pyswarms/base/base_discrete.py
pyswarms/base/base_single.py
pyswarms/discrete/__init__.py
pyswarms/discrete/binary.py
pyswarms/single/__init__.py
pyswarms/single/general_optimizer.py
pyswarms/single/global_best.py
pyswarms/single/local_best.py
pyswarms/utils/__init__.py
pyswarms/utils/decorators/__init__.py
pyswarms/utils/decorators/decorators.py
pyswarms/utils/functions/__init__.py
pyswarms/utils/functions/single_obj.py
pyswarms/utils/plotters/__init__.py
pyswarms/utils/plotters/formatters.py
pyswarms/utils/plotters/plotters.py
pyswarms/utils/reporter/__init__.py
pyswarms/utils/reporter/reporter.py
pyswarms/utils/search/__init__.py
pyswarms/utils/search/base_search.py
pyswarms/utils/search/grid_search.py
pyswarms/utils/search/random_search.py