Metadata-Version: 1.0
Name: csip-cosu
Version: 1.2.8
Summary: CSIP - Calibration Optimization Sensitivity and Uncertainty (COSU) Analysis Library
Home-page: http://alm.engr.colostate.edu/cb/project/csip
Author: Olaf David
Author-email: odavid@colostate.edu
License: MIT
Platform: UNKNOWN
